carconnectivity_plugin_mqtt_homeassistant-0.6.3.dist-info/licenses/LICENSE
carconnectivity_plugins/mqtt_homeassistant/__init__.py
carconnectivity_plugins/mqtt_homeassistant/_version.py
carconnectivity_plugins/mqtt_homeassistant/plugin.py
carconnectivity_plugins/mqtt_homeassistant/ui/plugin_ui.py
carconnectivity_plugin_mqtt_homeassistant-0.6.3.dist-info/METADATA
carconnectivity_plugin_mqtt_homeassistant-0.6.3.dist-info/WHEEL
carconnectivity_plugin_mqtt_homeassistant-0.6.3.dist-info/top_level.txt
carconnectivity_plugin_mqtt_homeassistant-0.6.3.dist-info/RECORD
